cfgmdl/__init__.py
cfgmdl/_version.py
cfgmdl/array.py
cfgmdl/choice.py
cfgmdl/configurable.py
cfgmdl/darray.py
cfgmdl/derived.py
cfgmdl/example.py
cfgmdl/function.py
cfgmdl/model.py
cfgmdl/param_holder.py
cfgmdl/parameter.py
cfgmdl/property.py
cfgmdl/ref.py
cfgmdl/tools.py
cfgmdl/unit.py
cfgmdl/utils.py
cfgmdl/version.py
cfgmdl-0.1.dist-info/LICENSE
cfgmdl-0.1.dist-info/METADATA
cfgmdl-0.1.dist-info/WHEEL
cfgmdl-0.1.dist-info/top_level.txt
cfgmdl-0.1.dist-info/RECORD
