Metadata-Version: 2.1
Name: cfgmdl
Version: 0.1
Summary: =Tools for configuration parsing and model building
Home-page: https://github.com/KIPAC/cfgmdl
Author: 
Author-email: 
License: UNKNOWN
Platform: UNKNOWN
Classifier: Development Status :: 4 - Beta
Classifier: License :: OSI Approved :: BSD License
Classifier: Intended Audience :: Developers
Classifier: Intended Audience :: Science/Research
Classifier: Operating System :: OS Independent
Classifier: Programming Language :: Python
Requires-Python: >=3.7
Requires-Dist: numpy
Requires-Dist: pyyaml
